{
  "$schema": "http://cyclonedx.org/schema/bom-1.5.schema.json",
  "bomFormat": "CycloneDX",
  "specVersion": "1.5",
  "serialNumber": "urn:uuid:b2d37e8c-3745-4498-b379-949245471f6b",
  "version": 1,
  "metadata": {
    "timestamp": "2023-09-26T06:55:10+00:00",
    "tools": [
      {
        "vendor": "aquasecurity",
        "name": "trivy",
        "version": "0.45.1"
      }
    ],
    "component": {
      "bom-ref": "8e83ad54-f8ae-4885-9fff-365d146c66e8",
      "type": "application",
      "name": ".",
      "properties": [
        {
          "name": "aquasecurity:trivy:SchemaVersion",
          "value": "2"
        }
      ]
    }
  },
  "components": [
    {
      "bom-ref": "0864bf85-5434-4a36-befc-b721f7eb12d6",
      "type": "application",
      "name": "common-alice/pom.xml",
      "properties": [
        {
          "name": "aquasecurity:trivy:Class",
          "value": "lang-pkgs"
        },
        {
          "name": "aquasecurity:trivy:Type",
          "value": "pom"
        }
      ]
    },
    {
      "bom-ref": "0dabfef1-fdda-4516-a384-7e88623de411",
      "type": "application",
      "name": "service-http-ecommerce/pom.xml",
      "properties": [
        {
          "name": "aquasecurity:trivy:Class",
          "value": "lang-pkgs"
        },
        {
          "name": "aquasecurity:trivy:Type",
          "value": "pom"
        }
      ]
    },
    {
      "bom-ref": "1eb5adb3-19be-4b74-a3c1-d2accf4b2998",
      "type": "application",
      "name": "common-bob/pom.xml",
      "properties": [
        {
          "name": "aquasecurity:trivy:Class",
          "value": "lang-pkgs"
        },
        {
          "name": "aquasecurity:trivy:Type",
          "value": "pom"
        }
      ]
    },
    {
      "bom-ref": "342cb33c-2228-4991-87e0-2cdcbca62cad",
      "type": "application",
      "name": "service-reading-report/pom.xml",
      "properties": [
        {
          "name": "aquasecurity:trivy:Class",
          "value": "lang-pkgs"
        },
        {
          "name": "aquasecurity:trivy:Type",
          "value": "pom"
        }
      ]
    },
    {
      "bom-ref": "392cebe1-7c0d-4198-bbc7-25ba8009cbc6",
      "type": "application",
      "name": "service-users/pom.xml",
      "properties": [
        {
          "name": "aquasecurity:trivy:Class",
          "value": "lang-pkgs"
        },
        {
          "name": "aquasecurity:trivy:Type",
          "value": "pom"
        }
      ]
    },
    {
      "bom-ref": "4103d9a3-9e1f-4a93-8d2c-07c11e141881",
      "type": "application",
      "name": "service-email/pom.xml",
      "properties": [
        {
          "name": "aquasecurity:trivy:Class",
          "value": "lang-pkgs"
        },
        {
          "name": "aquasecurity:trivy:Type",
          "value": "pom"
        }
      ]
    },
    {
      "bom-ref": "438a2713-4133-4090-8939-bbc400fa1971",
      "type": "application",
      "name": "service-email-new-order/pom.xml",
      "properties": [
        {
          "name": "aquasecurity:trivy:Class",
          "value": "lang-pkgs"
        },
        {
          "name": "aquasecurity:trivy:Type",
          "value": "pom"
        }
      ]
    },
    {
      "bom-ref": "45cebb50-92f5-4991-81b0-92a1cbe09390",
      "type": "application",
      "name": "service-new-order/pom.xml",
      "properties": [
        {
          "name": "aquasecurity:trivy:Class",
          "value": "lang-pkgs"
        },
        {
          "name": "aquasecurity:trivy:Type",
          "value": "pom"
        }
      ]
    },
    {
      "bom-ref": "82cca740-2d71-4c4a-bf7d-a5484b9ba1ec",
      "type": "application",
      "name": "common-database/pom.xml",
      "properties": [
        {
          "name": "aquasecurity:trivy:Class",
          "value": "lang-pkgs"
        },
        {
          "name": "aquasecurity:trivy:Type",
          "value": "pom"
        }
      ]
    },
    {
      "bom-ref": "a94be8c2-1cbc-49e2-a4ce-4d4450025eab",
      "type": "application",
      "name": "pom.xml",
      "properties": [
        {
          "name": "aquasecurity:trivy:Class",
          "value": "lang-pkgs"
        },
        {
          "name": "aquasecurity:trivy:Type",
          "value": "pom"
        }
      ]
    },
    {
      "bom-ref": "db225295-c694-4628-8640-c2ad1f711942",
      "type": "application",
      "name": "common-kafka/pom.xml",
      "properties": [
        {
          "name": "aquasecurity:trivy:Class",
          "value": "lang-pkgs"
        },
        {
          "name": "aquasecurity:trivy:Type",
          "value": "pom"
        }
      ]
    },
    {
      "bom-ref": "eaf0de27-628e-4572-ab12-6c3a9b98ecc1",
      "type": "application",
      "name": "service-fraud-detector/pom.xml",
      "properties": [
        {
          "name": "aquasecurity:trivy:Class",
          "value": "lang-pkgs"
        },
        {
          "name": "aquasecurity:trivy:Type",
          "value": "pom"
        }
      ]
    },
    {
      "bom-ref": "f632edda-480c-463c-8511-d7faf05ca7c7",
      "type": "application",
      "name": "service-log/pom.xml",
      "properties": [
        {
          "name": "aquasecurity:trivy:Class",
          "value": "lang-pkgs"
        },
        {
          "name": "aquasecurity:trivy:Type",
          "value": "pom"
        }
      ]
    },
    {
      "bom-ref": "pkg:maven/aopalliance/aopalliance@1.0",
      "type": "library",
      "name": "aopalliance:aopalliance",
      "version": "1.0",
      "licenses": [
        {
          "license": {
            "name": "Unlicense"
          }
        }
      ],
      "purl": "pkg:maven/aopalliance/aopalliance@1.0",
      "properties": [
        {
          "name": "aquasecurity:trivy:PkgID",
          "value": "aopalliance:aopalliance:1.0"
        },
        {
          "name": "aquasecurity:trivy:PkgType",
          "value": "pom"
        }
      ]
    },
    {
      "bom-ref": "pkg:maven/br.com.wasp/common-database@1.0-SNAPSHOT",
      "type": "library",
      "name": "br.com.wasp:common-database",
      "version": "1.0-SNAPSHOT",
      "purl": "pkg:maven/br.com.wasp/common-database@1.0-SNAPSHOT",
      "properties": [
        {
          "name": "aquasecurity:trivy:PkgID",
          "value": "br.com.wasp:common-database:1.0-SNAPSHOT"
        },
        {
          "name": "aquasecurity:trivy:PkgType",
          "value": "pom"
        }
      ]
    },
    {
      "bom-ref": "pkg:maven/br.com.wasp/common-kafka@1.0-SNAPSHOT",
      "type": "library",
      "name": "br.com.wasp:common-kafka",
      "version": "1.0-SNAPSHOT",
      "purl": "pkg:maven/br.com.wasp/common-kafka@1.0-SNAPSHOT",
      "properties": [
        {
          "name": "aquasecurity:trivy:PkgID",
          "value": "br.com.wasp:common-kafka:1.0-SNAPSHOT"
        },
        {
          "name": "aquasecurity:trivy:PkgType",
          "value": "pom"
        }
      ]
    },
    {
      "bom-ref": "pkg:maven/br.com.wasp/ecommerce@1.0-SNAPSHOT",
      "type": "library",
      "name": "br.com.wasp:ecommerce",
      "version": "1.0-SNAPSHOT",
      "purl": "pkg:maven/br.com.wasp/ecommerce@1.0-SNAPSHOT",
      "properties": [
        {
          "name": "aquasecurity:trivy:PkgID",
          "value": "br.com.wasp:ecommerce:1.0-SNAPSHOT"
        },
        {
          "name": "aquasecurity:trivy:PkgType",
          "value": "pom"
        }
      ]
    },
    {
      "bom-ref": "pkg:maven/br.com.wasp/service-email-new-order@1.0-SNAPSHOT",
      "type": "library",
      "name": "br.com.wasp:service-email-new-order",
      "version": "1.0-SNAPSHOT",
      "purl": "pkg:maven/br.com.wasp/service-email-new-order@1.0-SNAPSHOT",
      "properties": [
        {
          "name": "aquasecurity:trivy:PkgID",
          "value": "br.com.wasp:service-email-new-order:1.0-SNAPSHOT"
        },
        {
          "name": "aquasecurity:trivy:PkgType",
          "value": "pom"
        }
      ]
    },
    {
      "bom-ref": "pkg:maven/br.com.wasp/service-email@1.0-SNAPSHOT",
      "type": "library",
      "name": "br.com.wasp:service-email",
      "version": "1.0-SNAPSHOT",
      "purl": "pkg:maven/br.com.wasp/service-email@1.0-SNAPSHOT",
      "properties": [
        {
          "name": "aquasecurity:trivy:PkgID",
          "value": "br.com.wasp:service-email:1.0-SNAPSHOT"
        },
        {
          "name": "aquasecurity:trivy:PkgType",
          "value": "pom"
        }
      ]
    },
    {
      "bom-ref": "pkg:maven/br.com.wasp/service-fraud-detector@1.0-SNAPSHOT",
      "type": "library",
      "name": "br.com.wasp:service-fraud-detector",
      "version": "1.0-SNAPSHOT",
      "purl": "pkg:maven/br.com.wasp/service-fraud-detector@1.0-SNAPSHOT",
      "properties": [
        {
          "name": "aquasecurity:trivy:PkgID",
          "value": "br.com.wasp:service-fraud-detector:1.0-SNAPSHOT"
        },
        {
          "name": "aquasecurity:trivy:PkgType",
          "value": "pom"
        }
      ]
    },
    {
      "bom-ref": "pkg:maven/br.com.wasp/service-http-ecommerce@1.0-SNAPSHOT",
      "type": "library",
      "name": "br.com.wasp:service-http-ecommerce",
      "version": "1.0-SNAPSHOT",
      "purl": "pkg:maven/br.com.wasp/service-http-ecommerce@1.0-SNAPSHOT",
      "properties": [
        {
          "name": "aquasecurity:trivy:PkgID",
          "value": "br.com.wasp:service-http-ecommerce:1.0-SNAPSHOT"
        },
        {
          "name": "aquasecurity:trivy:PkgType",
          "value": "pom"
        }
      ]
    },
    {
      "bom-ref": "pkg:maven/br.com.wasp/service-log@1.0-SNAPSHOT",
      "type": "library",
      "name": "br.com.wasp:service-log",
      "version": "1.0-SNAPSHOT",
      "purl": "pkg:maven/br.com.wasp/service-log@1.0-SNAPSHOT",
      "properties": [
        {
          "name": "aquasecurity:trivy:PkgID",
          "value": "br.com.wasp:service-log:1.0-SNAPSHOT"
        },
        {
          "name": "aquasecurity:trivy:PkgType",
          "value": "pom"
        }
      ]
    },
    {
      "bom-ref": "pkg:maven/br.com.wasp/service-new-order@1.0-SNAPSHOT",
      "type": "library",
      "name": "br.com.wasp:service-new-order",
      "version": "1.0-SNAPSHOT",
      "purl": "pkg:maven/br.com.wasp/service-new-order@1.0-SNAPSHOT",
      "properties": [
        {
          "name": "aquasecurity:trivy:PkgID",
          "value": "br.com.wasp:service-new-order:1.0-SNAPSHOT"
        },
        {
          "name": "aquasecurity:trivy:PkgType",
          "value": "pom"
        }
      ]
    },
    {
      "bom-ref": "pkg:maven/br.com.wasp/service-reading-report@1.0-SNAPSHOT",
      "type": "library",
      "name": "br.com.wasp:service-reading-report",
      "version": "1.0-SNAPSHOT",
      "purl": "pkg:maven/br.com.wasp/service-reading-report@1.0-SNAPSHOT",
      "properties": [
        {
          "name": "aquasecurity:trivy:PkgID",
          "value": "br.com.wasp:service-reading-report:1.0-SNAPSHOT"
        },
        {
          "name": "aquasecurity:trivy:PkgType",
          "value": "pom"
        }
      ]
    },
    {
      "bom-ref": "pkg:maven/br.com.wasp/service-users@1.0-SNAPSHOT",
      "type": "library",
      "name": "br.com.wasp:service-users",
      "version": "1.0-SNAPSHOT",
      "purl": "pkg:maven/br.com.wasp/service-users@1.0-SNAPSHOT",
      "properties": [
        {
          "name": "aquasecurity:trivy:PkgID",
          "value": "br.com.wasp:service-users:1.0-SNAPSHOT"
        },
        {
          "name": "aquasecurity:trivy:PkgType",
          "value": "pom"
        }
      ]
    },
    {
      "bom-ref": "pkg:maven/cglib/cglib@3.1",
      "type": "library",
      "name": "cglib:cglib",
      "version": "3.1",
      "licenses": [
        {
          "license": {
            "name": "ASF 2.0"
          }
        }
      ],
      "purl": "pkg:maven/cglib/cglib@3.1",
      "properties": [
        {
          "name": "aquasecurity:trivy:PkgID",
          "value": "cglib:cglib:3.1"
        },
        {
          "name": "aquasecurity:trivy:PkgType",
          "value": "pom"
        }
      ]
    },
    {
      "bom-ref": "pkg:maven/ch.qos.logback/logback-classic@1.2.3",
      "type": "library",
      "name": "ch.qos.logback:logback-classic",
      "version": "1.2.3",
      "licenses": [
        {
          "license": {
            "name": "Eclipse Public License - v 1.0"
          }
        },
        {
          "license": {
            "name": "GNU Lesser General Public License"
          }
        }
      ],
      "purl": "pkg:maven/ch.qos.logback/logback-classic@1.2.3",
      "properties": [
        {
          "name": "aquasecurity:trivy:PkgID",
          "value": "ch.qos.logback:logback-classic:1.2.3"
        },
        {
          "name": "aquasecurity:trivy:PkgType",
          "value": "pom"
        }
      ]
    },
    {
      "bom-ref": "pkg:maven/ch.qos.logback/logback-core@1.2.3",
      "type": "library",
      "name": "ch.qos.logback:logback-core",
      "version": "1.2.3",
      "licenses": [
        {
          "license": {
            "name": "Eclipse Public License - v 1.0"
          }
        },
        {
          "license": {
            "name": "GNU Lesser General Public License"
          }
        }
      ],
      "purl": "pkg:maven/ch.qos.logback/logback-core@1.2.3",
      "properties": [
        {
          "name": "aquasecurity:trivy:PkgID",
          "value": "ch.qos.logback:logback-core:1.2.3"
        },
        {
          "name": "aquasecurity:trivy:PkgType",
          "value": "pom"
        }
      ]
    },
    {
      "bom-ref": "pkg:maven/com.alibaba/druid-spring-boot-starter@1.1.10",
      "type": "library",
      "name": "com.alibaba:druid-spring-boot-starter",
      "version": "1.1.10",
      "licenses": [
        {
          "license": {
            "name": "Apache 2"
          }
        }
      ],
      "purl": "pkg:maven/com.alibaba/druid-spring-boot-starter@1.1.10",
      "properties": [
        {
          "name": "aquasecurity:trivy:PkgID",
          "value": "com.alibaba:druid-spring-boot-starter:1.1.10"
        },
        {
          "name": "aquasecurity:trivy:PkgType",
          "value": "pom"
        }
      ]
    },
    {
      "bom-ref": "pkg:maven/com.alibaba/druid@1.1.10",
      "type": "library",
      "name": "com.alibaba:druid",
      "version": "1.1.10",
      "licenses": [
        {
          "license": {
            "name": "Apache 2"
          }
        }
      ],
      "purl": "pkg:maven/com.alibaba/druid@1.1.10",
      "properties": [
        {
          "name": "aquasecurity:trivy:PkgID",
          "value": "com.alibaba:druid:1.1.10"
        },
        {
          "name": "aquasecurity:trivy:PkgType",
          "value": "pom"
        }
      ]
    },
    {
      "bom-ref": "pkg:maven/com.alibaba/fastjson@1.2.60",
      "type": "library",
      "name": "com.alibaba:fastjson",
      "version": "1.2.60",
      "licenses": [
        {
          "license": {
            "name": "Apache 2"
          }
        }
      ],
      "purl": "pkg:maven/com.alibaba/fastjson@1.2.60",
      "properties": [
        {
          "name": "aquasecurity:trivy:PkgID",
          "value": "com.alibaba:fastjson:1.2.60"
        },
        {
          "name": "aquasecurity:trivy:PkgType",
          "value": "pom"
        }
      ]
    },
    {
      "bom-ref": "pkg:maven/com.baomidou/mybatis-plus-annotation@3.1.1",
      "type": "library",
      "name": "com.baomidou:mybatis-plus-annotation",
      "version": "3.1.1",
      "licenses": [
        {
          "license": {
            "name": "The Apache License, Version 2.0"
          }
        }
      ],
      "purl": "pkg:maven/com.baomidou/mybatis-plus-annotation@3.1.1",
      "properties": [
        {
          "name": "aquasecurity:trivy:PkgID",
          "value": "com.baomidou:mybatis-plus-annotation:3.1.1"
        },
        {
          "name": "aquasecurity:trivy:PkgType",
          "value": "pom"
        }
      ]
    },
    {
      "bom-ref": "pkg:maven/com.baomidou/mybatis-plus-boot-starter@3.1.1",
      "type": "library",
      "name": "com.baomidou:mybatis-plus-boot-starter",
      "version": "3.1.1",
      "licenses": [
        {
          "license": {
            "name": "The Apache License, Version 2.0"
          }
        }
      ],
      "purl": "pkg:maven/com.baomidou/mybatis-plus-boot-starter@3.1.1",
      "properties": [
        {
          "name": "aquasecurity:trivy:PkgID",
          "value": "com.baomidou:mybatis-plus-boot-starter:3.1.1"
        },
        {
          "name": "aquasecurity:trivy:PkgType",
          "value": "pom"
        }
      ]
    },
    {
      "bom-ref": "pkg:maven/com.baomidou/mybatis-plus-core@3.1.1",
      "type": "library",
      "name": "com.baomidou:mybatis-plus-core",
      "version": "3.1.1",
      "licenses": [
        {
          "license": {
            "name": "The Apache License, Version 2.0"
          }
        }
      ],
      "purl": "pkg:maven/com.baomidou/mybatis-plus-core@3.1.1",
      "properties": [
        {
          "name": "aquasecurity:trivy:PkgID",
          "value": "com.baomidou:mybatis-plus-core:3.1.1"
        },
        {
          "name": "aquasecurity:trivy:PkgType",
          "value": "pom"
        }
      ]
    },
    {
      "bom-ref": "pkg:maven/com.baomidou/mybatis-plus-extension@3.1.1",
      "type": "library",
      "name": "com.baomidou:mybatis-plus-extension",
      "version": "3.1.1",
      "licenses": [
        {
          "license": {
            "name": "The Apache License, Version 2.0"
          }
        }
      ],
      "purl": "pkg:maven/com.baomidou/mybatis-plus-extension@3.1.1",
      "properties": [
        {
          "name": "aquasecurity:trivy:PkgID",
          "value": "com.baomidou:mybatis-plus-extension:3.1.1"
        },
        {
          "name": "aquasecurity:trivy:PkgType",
          "value": "pom"
        }
      ]
    },
    {
      "bom-ref": "pkg:maven/com.baomidou/mybatis-plus@3.1.1",
      "type": "library",
      "name": "com.baomidou:mybatis-plus",
      "version": "3.1.1",
      "licenses": [
        {
          "license": {
            "name": "The Apache License, Version 2.0"
          }
        }
      ],
      "purl": "pkg:maven/com.baomidou/mybatis-plus@3.1.1",
      "properties": [
        {
          "name": "aquasecurity:trivy:PkgID",
          "value": "com.baomidou:mybatis-plus:3.1.1"
        },
        {
          "name": "aquasecurity:trivy:PkgType",
          "value": "pom"
        }
      ]
    },
    {
      "bom-ref": "pkg:maven/com.github.ben-manes.caffeine/caffeine@2.7.0",
      "type": "library",
      "name": "com.github.ben-manes.caffeine:caffeine",
      "version": "2.7.0",
      "licenses": [
        {
          "license": {
            "name": "Apache License, Version 2.0"
          }
        }
      ],
      "purl": "pkg:maven/com.github.ben-manes.caffeine/caffeine@2.7.0",
      "properties": [
        {
          "name": "aquasecurity:trivy:PkgID",
          "value": "com.github.ben-manes.caffeine:caffeine:2.7.0"
        },
        {
          "name": "aquasecurity:trivy:PkgType",
          "value": "pom"
        }
      ]
    },
    {
      "bom-ref": "pkg:maven/com.github.jsqlparser/jsqlparser@1.2",
      "type": "library",
      "name": "com.github.jsqlparser:jsqlparser",
      "version": "1.2",
      "licenses": [
        {
          "license": {
            "name": "GNU Library"
          }
        },
        {
          "license": {
            "name": "Lesser General Public License (LGPL) V2.1"
          }
        },
        {
          "license": {
            "name": "The Apache Software License, Version 2.0"
          }
        }
      ],
      "purl": "pkg:maven/com.github.jsqlparser/jsqlparser@1.2",
      "properties": [
        {
          "name": "aquasecurity:trivy:PkgID",
          "value": "com.github.jsqlparser:jsqlparser:1.2"
        },
        {
          "name": "aquasecurity:trivy:PkgType",
          "value": "pom"
        }
      ]
    },
    {
      "bom-ref": "pkg:maven/com.github.luben/zstd-jni@1.4.0-1",
      "type": "library",
      "name": "com.github.luben:zstd-jni",
      "version": "1.4.0-1",
      "licenses": [
        {
          "license": {
            "name": "BSD 2-Clause License"
          }
        }
      ],
      "purl": "pkg:maven/com.github.luben/zstd-jni@1.4.0-1",
      "properties": [
        {
          "name": "aquasecurity:trivy:PkgID",
          "value": "com.github.luben:zstd-jni:1.4.0-1"
        },
        {
          "name": "aquasecurity:trivy:PkgType",
          "value": "pom"
        }
      ]
    },
    {
      "bom-ref": "pkg:maven/com.google.code.gson/gson@2.8.6",
      "type": "library",
      "name": "com.google.code.gson:gson",
      "version": "2.8.6",
      "licenses": [
        {
          "license": {
            "name": "Apache-2.0"
          }
        }
      ],
      "purl": "pkg:maven/com.google.code.gson/gson@2.8.6",
      "properties": [
        {
          "name": "aquasecurity:trivy:PkgID",
          "value": "com.google.code.gson:gson:2.8.6"
        },
        {
          "name": "aquasecurity:trivy:PkgType",
          "value": "pom"
        }
      ]
    },
    {
      "bom-ref": "pkg:maven/com.google.errorprone/error_prone_annotations@2.3.3",
      "type": "library",
      "name": "com.google.errorprone:error_prone_annotations",
      "version": "2.3.3",
      "licenses": [
        {
          "license": {
            "name": "Apache-2.0"
          }
        }
      ],
      "purl": "pkg:maven/com.google.errorprone/error_prone_annotations@2.3.3",
      "properties": [
        {
          "name": "aquasecurity:trivy:PkgID",
          "value": "com.google.errorprone:error_prone_annotations:2.3.3"
        },
        {
          "name": "aquasecurity:trivy:PkgType",
          "value": "pom"
        }
      ]
    },
    {
      "bom-ref": "pkg:maven/com.google.protobuf/protobuf-java@3.7.1",
      "type": "library",
      "name": "com.google.protobuf:protobuf-java",
      "version": "3.7.1",
      "licenses": [
        {
          "license": {
            "name": "3-Clause BSD License"
          }
        }
      ],
      "purl": "pkg:maven/com.google.protobuf/protobuf-java@3.7.1",
      "properties": [
        {
          "name": "aquasecurity:trivy:PkgID",
          "value": "com.google.protobuf:protobuf-java:3.7.1"
        },
        {
          "name": "aquasecurity:trivy:PkgType",
          "value": "pom"
        }
      ]
    },
    {
      "bom-ref": "pkg:maven/com.typesafe/config@1.2.1",
      "type": "library",
      "name": "com.typesafe:config",
      "version": "1.2.1",
      "licenses": [
        {
          "license": {
            "name": "Apache License, Version 2.0"
          }
        }
      ],
      "purl": "pkg:maven/com.typesafe/config@1.2.1",
      "properties": [
        {
          "name": "aquasecurity:trivy:PkgID",
          "value": "com.typesafe:config:1.2.1"
        },
        {
          "name": "aquasecurity:trivy:PkgType",
          "value": "pom"
        }
      ]
    },
    {
      "bom-ref": "pkg:maven/com.zaxxer/HikariCP@3.2.0",
      "type": "library",
      "name": "com.zaxxer:HikariCP",
      "version": "3.2.0",
      "licenses": [
        {
          "license": {
            "name": "The Apache Software License, Version 2.0"
          }
        }
      ],
      "purl": "pkg:maven/com.zaxxer/HikariCP@3.2.0",
      "properties": [
        {
          "name": "aquasecurity:trivy:PkgID",
          "value": "com.zaxxer:HikariCP:3.2.0"
        },
        {
          "name": "aquasecurity:trivy:PkgType",
          "value": "pom"
        }
      ]
    },
    {
      "bom-ref": "pkg:maven/commons-lang/commons-lang@2.6",
      "type": "library",
      "name": "commons-lang:commons-lang",
      "version": "2.6",
      "licenses": [
        {
          "license": {
            "name": "The Apache Software License, Version 2.0"
          }
        }
      ],
      "purl": "pkg:maven/commons-lang/commons-lang@2.6",
      "properties": [
        {
          "name": "aquasecurity:trivy:PkgID",
          "value": "commons-lang:commons-lang:2.6"
        },
        {
          "name": "aquasecurity:trivy:PkgType",
          "value": "pom"
        }
      ]
    },
    {
      "bom-ref": "pkg:maven/commons-logging/commons-logging@1.2",
      "type": "library",
      "name": "commons-logging:commons-logging",
      "version": "1.2",
      "licenses": [
        {
          "license": {
            "name": "The Apache Software License, Version 2.0"
          }
        }
      ],
      "purl": "pkg:maven/commons-logging/commons-logging@1.2",
      "properties": [
        {
          "name": "aquasecurity:trivy:PkgID",
          "value": "commons-logging:commons-logging:1.2"
        },
        {
          "name": "aquasecurity:trivy:PkgType",
          "value": "pom"
        }
      ]
    },
    {
      "bom-ref": "pkg:maven/commons-pool/commons-pool@1.6",
      "type": "library",
      "name": "commons-pool:commons-pool",
      "version": "1.6",
      "licenses": [
        {
          "license": {
            "name": "The Apache Software License, Version 2.0"
          }
        }
      ],
      "purl": "pkg:maven/commons-pool/commons-pool@1.6",
      "properties": [
        {
          "name": "aquasecurity:trivy:PkgID",
          "value": "commons-pool:commons-pool:1.6"
        },
        {
          "name": "aquasecurity:trivy:PkgType",
          "value": "pom"
        }
      ]
    },
    {
      "bom-ref": "pkg:maven/io.netty/netty-all@4.1.30.Final",
      "type": "library",
      "name": "io.netty:netty-all",
      "version": "4.1.30.Final",
      "licenses": [
        {
          "license": {
            "name": "Apache License, Version 2.0"
          }
        }
      ],
      "purl": "pkg:maven/io.netty/netty-all@4.1.30.Final",
      "properties": [
        {
          "name": "aquasecurity:trivy:PkgID",
          "value": "io.netty:netty-all:4.1.30.Final"
        },
        {
          "name": "aquasecurity:trivy:PkgType",
          "value": "pom"
        }
      ]
    },
    {
      "bom-ref": "pkg:maven/io.seata/seata-all@1.1.0",
      "type": "library",
      "name": "io.seata:seata-all",
      "version": "1.1.0",
      "licenses": [
        {
          "license": {
            "name": "Apache License, Version 2.0"
          }
        }
      ],
      "purl": "pkg:maven/io.seata/seata-all@1.1.0",
      "properties": [
        {
          "name": "aquasecurity:trivy:PkgID",
          "value": "io.seata:seata-all:1.1.0"
        },
        {
          "name": "aquasecurity:trivy:PkgType",
          "value": "pom"
        }
      ]
    },
    {
      "bom-ref": "pkg:maven/javax.annotation/javax.annotation-api@1.3.2",
      "type": "library",
      "name": "javax.annotation:javax.annotation-api",
      "version": "1.3.2",
      "licenses": [
        {
          "license": {
            "name": "CDDL + GPLv2 with classpath exception"
          }
        }
      ],
      "purl": "pkg:maven/javax.annotation/javax.annotation-api@1.3.2",
      "properties": [
        {
          "name": "aquasecurity:trivy:PkgID",
          "value": "javax.annotation:javax.annotation-api:1.3.2"
        },
        {
          "name": "aquasecurity:trivy:PkgType",
          "value": "pom"
        }
      ]
    },
    {
      "bom-ref": "pkg:maven/javax.servlet/javax.servlet-api@3.1.0",
      "type": "library",
      "name": "javax.servlet:javax.servlet-api",
      "version": "3.1.0",
      "licenses": [
        {
          "license": {
            "name": "CDDL + GPLv2 with classpath exception"
          }
        }
      ],
      "purl": "pkg:maven/javax.servlet/javax.servlet-api@3.1.0",
      "properties": [
        {
          "name": "aquasecurity:trivy:PkgID",
          "value": "javax.servlet:javax.servlet-api:3.1.0"
        },
        {
          "name": "aquasecurity:trivy:PkgType",
          "value": "pom"
        }
      ]
    },
    {
      "bom-ref": "pkg:maven/mysql/mysql-connector-java@5.1.39",
      "type": "library",
      "name": "mysql:mysql-connector-java",
      "version": "5.1.39",
      "licenses": [
        {
          "license": {
            "name": "The GNU General Public License, Version 2"
          }
        }
      ],
      "purl": "pkg:maven/mysql/mysql-connector-java@5.1.39",
      "properties": [
        {
          "name": "aquasecurity:trivy:PkgID",
          "value": "mysql:mysql-connector-java:5.1.39"
        },
        {
          "name": "aquasecurity:trivy:PkgType",
          "value": "pom"
        }
      ]
    },
    {
      "bom-ref": "pkg:maven/org.apache.ant/ant-antunit@1.3",
      "type": "library",
      "name": "org.apache.ant:ant-antunit",
      "version": "1.3",
      "licenses": [
        {
          "license": {
            "name": "The Apache Software License, Version 2.0"
          }
        }
      ],
      "purl": "pkg:maven/org.apache.ant/ant-antunit@1.3",
      "properties": [
        {
          "name": "aquasecurity:trivy:PkgID",
          "value": "org.apache.ant:ant-antunit:1.3"
        },
        {
          "name": "aquasecurity:trivy:PkgType",
          "value": "pom"
        }
      ]
    },
    {
      "bom-ref": "pkg:maven/org.apache.ant/ant@1.7.1",
      "type": "library",
      "name": "org.apache.ant:ant",
      "version": "1.7.1",
      "purl": "pkg:maven/org.apache.ant/ant@1.7.1",
      "properties": [
        {
          "name": "aquasecurity:trivy:PkgID",
          "value": "org.apache.ant:ant:1.7.1"
        },
        {
          "name": "aquasecurity:trivy:PkgType",
          "value": "pom"
        }
      ]
    },
    {
      "bom-ref": "pkg:maven/org.apache.commons/commons-pool2@2.4.2",
      "type": "library",
      "name": "org.apache.commons:commons-pool2",
      "version": "2.4.2",
      "licenses": [
        {
          "license": {
            "name": "The Apache Software License, Version 2.0"
          }
        }
      ],
      "purl": "pkg:maven/org.apache.commons/commons-pool2@2.4.2",
      "properties": [
        {
          "name": "aquasecurity:trivy:PkgID",
          "value": "org.apache.commons:commons-pool2:2.4.2"
        },
        {
          "name": "aquasecurity:trivy:PkgType",
          "value": "pom"
        }
      ]
    },
    {
      "bom-ref": "pkg:maven/org.apache.derby/derby@10.14.2.0",
      "type": "library",
      "name": "org.apache.derby:derby",
      "version": "10.14.2.0",
      "licenses": [
        {
          "license": {
            "name": "Apache 2"
          }
        }
      ],
      "purl": "pkg:maven/org.apache.derby/derby@10.14.2.0",
      "properties": [
        {
          "name": "aquasecurity:trivy:PkgID",
          "value": "org.apache.derby:derby:10.14.2.0"
        },
        {
          "name": "aquasecurity:trivy:PkgType",
          "value": "pom"
        }
      ]
    },
    {
      "bom-ref": "pkg:maven/org.apache.kafka/kafka-clients@2.3.1",
      "type": "library",
      "name": "org.apache.kafka:kafka-clients",
      "version": "2.3.1",
      "licenses": [
        {
          "license": {
            "name": "The Apache Software License, Version 2.0"
          }
        }
      ],
      "purl": "pkg:maven/org.apache.kafka/kafka-clients@2.3.1",
      "properties": [
        {
          "name": "aquasecurity:trivy:PkgID",
          "value": "org.apache.kafka:kafka-clients:2.3.1"
        },
        {
          "name": "aquasecurity:trivy:PkgType",
          "value": "pom"
        }
      ]
    },
    {
      "bom-ref": "pkg:maven/org.apache.logging.log4j/log4j-api@2.11.1",
      "type": "library",
      "name": "org.apache.logging.log4j:log4j-api",
      "version": "2.11.1",
      "licenses": [
        {
          "license": {
            "name": "Apache License, Version 2.0"
          }
        }
      ],
      "purl": "pkg:maven/org.apache.logging.log4j/log4j-api@2.11.1",
      "properties": [
        {
          "name": "aquasecurity:trivy:PkgID",
          "value": "org.apache.logging.log4j:log4j-api:2.11.1"
        },
        {
          "name": "aquasecurity:trivy:PkgType",
          "value": "pom"
        }
      ]
    },
    {
      "bom-ref": "pkg:maven/org.apache.logging.log4j/log4j-to-slf4j@2.11.1",
      "type": "library",
      "name": "org.apache.logging.log4j:log4j-to-slf4j",
      "version": "2.11.1",
      "licenses": [
        {
          "license": {
            "name": "Apache License, Version 2.0"
          }
        }
      ],
      "purl": "pkg:maven/org.apache.logging.log4j/log4j-to-slf4j@2.11.1",
      "properties": [
        {
          "name": "aquasecurity:trivy:PkgID",
          "value": "org.apache.logging.log4j:log4j-to-slf4j:2.11.1"
        },
        {
          "name": "aquasecurity:trivy:PkgType",
          "value": "pom"
        }
      ]
    },
    {
      "bom-ref": "pkg:maven/org.checkerframework/checker-qual@2.6.0",
      "type": "library",
      "name": "org.checkerframework:checker-qual",
      "version": "2.6.0",
      "licenses": [
        {
          "license": {
            "name": "The MIT License"
          }
        }
      ],
      "purl": "pkg:maven/org.checkerframework/checker-qual@2.6.0",
      "properties": [
        {
          "name": "aquasecurity:trivy:PkgID",
          "value": "org.checkerframework:checker-qual:2.6.0"
        },
        {
          "name": "aquasecurity:trivy:PkgType",
          "value": "pom"
        }
      ]
    },
    {
      "bom-ref": "pkg:maven/org.eclipse.jetty/jetty-http@9.4.23.v20191118",
      "type": "library",
      "name": "org.eclipse.jetty:jetty-http",
      "version": "9.4.23.v20191118",
      "licenses": [
        {
          "license": {
            "name": "Apache Software License - Version 2.0"
          }
        },
        {
          "license": {
            "name": "Eclipse Public License - Version 1.0"
          }
        }
      ],
      "purl": "pkg:maven/org.eclipse.jetty/jetty-http@9.4.23.v20191118",
      "properties": [
        {
          "name": "aquasecurity:trivy:PkgID",
          "value": "org.eclipse.jetty:jetty-http:9.4.23.v20191118"
        },
        {
          "name": "aquasecurity:trivy:PkgType",
          "value": "pom"
        }
      ]
    },
    {
      "bom-ref": "pkg:maven/org.eclipse.jetty/jetty-io@9.4.23.v20191118",
      "type": "library",
      "name": "org.eclipse.jetty:jetty-io",
      "version": "9.4.23.v20191118",
      "licenses": [
        {
          "license": {
            "name": "Apache Software License - Version 2.0"
          }
        },
        {
          "license": {
            "name": "Eclipse Public License - Version 1.0"
          }
        }
      ],
      "purl": "pkg:maven/org.eclipse.jetty/jetty-io@9.4.23.v20191118",
      "properties": [
        {
          "name": "aquasecurity:trivy:PkgID",
          "value": "org.eclipse.jetty:jetty-io:9.4.23.v20191118"
        },
        {
          "name": "aquasecurity:trivy:PkgType",
          "value": "pom"
        }
      ]
    },
    {
      "bom-ref": "pkg:maven/org.eclipse.jetty/jetty-security@9.4.23.v20191118",
      "type": "library",
      "name": "org.eclipse.jetty:jetty-security",
      "version": "9.4.23.v20191118",
      "licenses": [
        {
          "license": {
            "name": "Apache Software License - Version 2.0"
          }
        },
        {
          "license": {
            "name": "Eclipse Public License - Version 1.0"
          }
        }
      ],
      "purl": "pkg:maven/org.eclipse.jetty/jetty-security@9.4.23.v20191118",
      "properties": [
        {
          "name": "aquasecurity:trivy:PkgID",
          "value": "org.eclipse.jetty:jetty-security:9.4.23.v20191118"
        },
        {
          "name": "aquasecurity:trivy:PkgType",
          "value": "pom"
        }
      ]
    },
    {
      "bom-ref": "pkg:maven/org.eclipse.jetty/jetty-server@9.4.23.v20191118",
      "type": "library",
      "name": "org.eclipse.jetty:jetty-server",
      "version": "9.4.23.v20191118",
      "licenses": [
        {
          "license": {
            "name": "Apache Software License - Version 2.0"
          }
        },
        {
          "license": {
            "name": "Eclipse Public License - Version 1.0"
          }
        }
      ],
      "purl": "pkg:maven/org.eclipse.jetty/jetty-server@9.4.23.v20191118",
      "properties": [
        {
          "name": "aquasecurity:trivy:PkgID",
          "value": "org.eclipse.jetty:jetty-server:9.4.23.v20191118"
        },
        {
          "name": "aquasecurity:trivy:PkgType",
          "value": "pom"
        }
      ]
    },
    {
      "bom-ref": "pkg:maven/org.eclipse.jetty/jetty-servlet@9.4.23.v20191118",
      "type": "library",
      "name": "org.eclipse.jetty:jetty-servlet",
      "version": "9.4.23.v20191118",
      "licenses": [
        {
          "license": {
            "name": "Apache Software License - Version 2.0"
          }
        },
        {
          "license": {
            "name": "Eclipse Public License - Version 1.0"
          }
        }
      ],
      "purl": "pkg:maven/org.eclipse.jetty/jetty-servlet@9.4.23.v20191118",
      "properties": [
        {
          "name": "aquasecurity:trivy:PkgID",
          "value": "org.eclipse.jetty:jetty-servlet:9.4.23.v20191118"
        },
        {
          "name": "aquasecurity:trivy:PkgType",
          "value": "pom"
        }
      ]
    },
    {
      "bom-ref": "pkg:maven/org.eclipse.jetty/jetty-util@9.4.23.v20191118",
      "type": "library",
      "name": "org.eclipse.jetty:jetty-util",
      "version": "9.4.23.v20191118",
      "licenses": [
        {
          "license": {
            "name": "Apache Software License - Version 2.0"
          }
        },
        {
          "license": {
            "name": "Eclipse Public License - Version 1.0"
          }
        }
      ],
      "purl": "pkg:maven/org.eclipse.jetty/jetty-util@9.4.23.v20191118",
      "properties": [
        {
          "name": "aquasecurity:trivy:PkgID",
          "value": "org.eclipse.jetty:jetty-util:9.4.23.v20191118"
        },
        {
          "name": "aquasecurity:trivy:PkgType",
          "value": "pom"
        }
      ]
    },
    {
      "bom-ref": "pkg:maven/org.lz4/lz4-java@1.6.0",
      "type": "library",
      "name": "org.lz4:lz4-java",
      "version": "1.6.0",
      "licenses": [
        {
          "license": {
            "name": "The Apache Software License, Version 2.0"
          }
        }
      ],
      "purl": "pkg:maven/org.lz4/lz4-java@1.6.0",
      "properties": [
        {
          "name": "aquasecurity:trivy:PkgID",
          "value": "org.lz4:lz4-java:1.6.0"
        },
        {
          "name": "aquasecurity:trivy:PkgType",
          "value": "pom"
        }
      ]
    },
    {
      "bom-ref": "pkg:maven/org.mybatis/mybatis-spring@2.0.1",
      "type": "library",
      "name": "org.mybatis:mybatis-spring",
      "version": "2.0.1",
      "licenses": [
        {
          "license": {
            "name": "The Apache Software License, Version 2.0"
          }
        }
      ],
      "purl": "pkg:maven/org.mybatis/mybatis-spring@2.0.1",
      "properties": [
        {
          "name": "aquasecurity:trivy:PkgID",
          "value": "org.mybatis:mybatis-spring:2.0.1"
        },
        {
          "name": "aquasecurity:trivy:PkgType",
          "value": "pom"
        }
      ]
    },
    {
      "bom-ref": "pkg:maven/org.mybatis/mybatis@3.5.1",
      "type": "library",
      "name": "org.mybatis:mybatis",
      "version": "3.5.1",
      "licenses": [
        {
          "license": {
            "name": "The Apache Software License, Version 2.0"
          }
        }
      ],
      "purl": "pkg:maven/org.mybatis/mybatis@3.5.1",
      "properties": [
        {
          "name": "aquasecurity:trivy:PkgID",
          "value": "org.mybatis:mybatis:3.5.1"
        },
        {
          "name": "aquasecurity:trivy:PkgType",
          "value": "pom"
        }
      ]
    },
    {
      "bom-ref": "pkg:maven/org.ow2.asm/asm@4.2",
      "type": "library",
      "name": "org.ow2.asm:asm",
      "version": "4.2",
      "licenses": [
        {
          "license": {
            "name": "BSD-3-Clause"
          }
        }
      ],
      "purl": "pkg:maven/org.ow2.asm/asm@4.2",
      "properties": [
        {
          "name": "aquasecurity:trivy:PkgID",
          "value": "org.ow2.asm:asm:4.2"
        },
        {
          "name": "aquasecurity:trivy:PkgType",
          "value": "pom"
        }
      ]
    },
    {
      "bom-ref": "pkg:maven/org.postgresql/postgresql@42.1.4",
      "type": "library",
      "name": "org.postgresql:postgresql",
      "version": "42.1.4",
      "licenses": [
        {
          "license": {
            "name": "BSD-2-Clause"
          }
        }
      ],
      "purl": "pkg:maven/org.postgresql/postgresql@42.1.4",
      "properties": [
        {
          "name": "aquasecurity:trivy:PkgID",
          "value": "org.postgresql:postgresql:42.1.4"
        },
        {
          "name": "aquasecurity:trivy:PkgType",
          "value": "pom"
        }
      ]
    },
    {
      "bom-ref": "pkg:maven/org.slf4j/jul-to-slf4j@1.7.25",
      "type": "library",
      "name": "org.slf4j:jul-to-slf4j",
      "version": "1.7.25",
      "licenses": [
        {
          "license": {
            "name": "MIT License"
          }
        }
      ],
      "purl": "pkg:maven/org.slf4j/jul-to-slf4j@1.7.25",
      "properties": [
        {
          "name": "aquasecurity:trivy:PkgID",
          "value": "org.slf4j:jul-to-slf4j:1.7.25"
        },
        {
          "name": "aquasecurity:trivy:PkgType",
          "value": "pom"
        }
      ]
    },
    {
      "bom-ref": "pkg:maven/org.slf4j/slf4j-api@1.7.26",
      "type": "library",
      "name": "org.slf4j:slf4j-api",
      "version": "1.7.26",
      "licenses": [
        {
          "license": {
            "name": "MIT License"
          }
        }
      ],
      "purl": "pkg:maven/org.slf4j/slf4j-api@1.7.26",
      "properties": [
        {
          "name": "aquasecurity:trivy:PkgID",
          "value": "org.slf4j:slf4j-api:1.7.26"
        },
        {
          "name": "aquasecurity:trivy:PkgType",
          "value": "pom"
        }
      ]
    },
    {
      "bom-ref": "pkg:maven/org.slf4j/slf4j-simple@1.7.29",
      "type": "library",
      "name": "org.slf4j:slf4j-simple",
      "version": "1.7.29",
      "licenses": [
        {
          "license": {
            "name": "MIT License"
          }
        }
      ],
      "purl": "pkg:maven/org.slf4j/slf4j-simple@1.7.29",
      "properties": [
        {
          "name": "aquasecurity:trivy:PkgID",
          "value": "org.slf4j:slf4j-simple:1.7.29"
        },
        {
          "name": "aquasecurity:trivy:PkgType",
          "value": "pom"
        }
      ]
    },
    {
      "bom-ref": "pkg:maven/org.springframework.boot/spring-boot-autoconfigure@1.5.12.RELEASE",
      "type": "library",
      "name": "org.springframework.boot:spring-boot-autoconfigure",
      "version": "1.5.12.RELEASE",
      "licenses": [
        {
          "license": {
            "name": "Apache License, Version 2.0"
          }
        }
      ],
      "purl": "pkg:maven/org.springframework.boot/spring-boot-autoconfigure@1.5.12.RELEASE",
      "properties": [
        {
          "name": "aquasecurity:trivy:PkgID",
          "value": "org.springframework.boot:spring-boot-autoconfigure:1.5.12.RELEASE"
        },
        {
          "name": "aquasecurity:trivy:PkgType",
          "value": "pom"
        }
      ]
    },
    {
      "bom-ref": "pkg:maven/org.springframework.boot/spring-boot-starter-jdbc@2.1.2.RELEASE",
      "type": "library",
      "name": "org.springframework.boot:spring-boot-starter-jdbc",
      "version": "2.1.2.RELEASE",
      "licenses": [
        {
          "license": {
            "name": "Apache License, Version 2.0"
          }
        }
      ],
      "purl": "pkg:maven/org.springframework.boot/spring-boot-starter-jdbc@2.1.2.RELEASE",
      "properties": [
        {
          "name": "aquasecurity:trivy:PkgID",
          "value": "org.springframework.boot:spring-boot-starter-jdbc:2.1.2.RELEASE"
        },
        {
          "name": "aquasecurity:trivy:PkgType",
          "value": "pom"
        }
      ]
    },
    {
      "bom-ref": "pkg:maven/org.springframework.boot/spring-boot-starter-logging@2.1.2.RELEASE",
      "type": "library",
      "name": "org.springframework.boot:spring-boot-starter-logging",
      "version": "2.1.2.RELEASE",
      "licenses": [
        {
          "license": {
            "name": "Apache License, Version 2.0"
          }
        }
      ],
      "purl": "pkg:maven/org.springframework.boot/spring-boot-starter-logging@2.1.2.RELEASE",
      "properties": [
        {
          "name": "aquasecurity:trivy:PkgID",
          "value": "org.springframework.boot:spring-boot-starter-logging:2.1.2.RELEASE"
        },
        {
          "name": "aquasecurity:trivy:PkgType",
          "value": "pom"
        }
      ]
    },
    {
      "bom-ref": "pkg:maven/org.springframework.boot/spring-boot-starter@2.1.2.RELEASE",
      "type": "library",
      "name": "org.springframework.boot:spring-boot-starter",
      "version": "2.1.2.RELEASE",
      "licenses": [
        {
          "license": {
            "name": "Apache License, Version 2.0"
          }
        }
      ],
      "purl": "pkg:maven/org.springframework.boot/spring-boot-starter@2.1.2.RELEASE",
      "properties": [
        {
          "name": "aquasecurity:trivy:PkgID",
          "value": "org.springframework.boot:spring-boot-starter:2.1.2.RELEASE"
        },
        {
          "name": "aquasecurity:trivy:PkgType",
          "value": "pom"
        }
      ]
    },
    {
      "bom-ref": "pkg:maven/org.springframework.boot/spring-boot@1.5.12.RELEASE",
      "type": "library",
      "name": "org.springframework.boot:spring-boot",
      "version": "1.5.12.RELEASE",
      "licenses": [
        {
          "license": {
            "name": "Apache License, Version 2.0"
          }
        }
      ],
      "purl": "pkg:maven/org.springframework.boot/spring-boot@1.5.12.RELEASE",
      "properties": [
        {
          "name": "aquasecurity:trivy:PkgID",
          "value": "org.springframework.boot:spring-boot:1.5.12.RELEASE"
        },
        {
          "name": "aquasecurity:trivy:PkgType",
          "value": "pom"
        }
      ]
    },
    {
      "bom-ref": "pkg:maven/org.springframework/spring-aop@4.3.23.RELEASE",
      "type": "library",
      "name": "org.springframework:spring-aop",
      "version": "4.3.23.RELEASE",
      "licenses": [
        {
          "license": {
            "name": "Apache License, Version 2.0"
          }
        }
      ],
      "purl": "pkg:maven/org.springframework/spring-aop@4.3.23.RELEASE",
      "properties": [
        {
          "name": "aquasecurity:trivy:PkgID",
          "value": "org.springframework:spring-aop:4.3.23.RELEASE"
        },
        {
          "name": "aquasecurity:trivy:PkgType",
          "value": "pom"
        }
      ]
    },
    {
      "bom-ref": "pkg:maven/org.springframework/spring-beans@4.3.23.RELEASE",
      "type": "library",
      "name": "org.springframework:spring-beans",
      "version": "4.3.23.RELEASE",
      "licenses": [
        {
          "license": {
            "name": "Apache License, Version 2.0"
          }
        }
      ],
      "purl": "pkg:maven/org.springframework/spring-beans@4.3.23.RELEASE",
      "properties": [
        {
          "name": "aquasecurity:trivy:PkgID",
          "value": "org.springframework:spring-beans:4.3.23.RELEASE"
        },
        {
          "name": "aquasecurity:trivy:PkgType",
          "value": "pom"
        }
      ]
    },
    {
      "bom-ref": "pkg:maven/org.springframework/spring-context@4.3.23.RELEASE",
      "type": "library",
      "name": "org.springframework:spring-context",
      "version": "4.3.23.RELEASE",
      "licenses": [
        {
          "license": {
            "name": "Apache License, Version 2.0"
          }
        }
      ],
      "purl": "pkg:maven/org.springframework/spring-context@4.3.23.RELEASE",
      "properties": [
        {
          "name": "aquasecurity:trivy:PkgID",
          "value": "org.springframework:spring-context:4.3.23.RELEASE"
        },
        {
          "name": "aquasecurity:trivy:PkgType",
          "value": "pom"
        }
      ]
    },
    {
      "bom-ref": "pkg:maven/org.springframework/spring-core@4.3.23.RELEASE",
      "type": "library",
      "name": "org.springframework:spring-core",
      "version": "4.3.23.RELEASE",
      "licenses": [
        {
          "license": {
            "name": "Apache License, Version 2.0"
          }
        }
      ],
      "purl": "pkg:maven/org.springframework/spring-core@4.3.23.RELEASE",
      "properties": [
        {
          "name": "aquasecurity:trivy:PkgID",
          "value": "org.springframework:spring-core:4.3.23.RELEASE"
        },
        {
          "name": "aquasecurity:trivy:PkgType",
          "value": "pom"
        }
      ]
    },
    {
      "bom-ref": "pkg:maven/org.springframework/spring-expression@4.3.23.RELEASE",
      "type": "library",
      "name": "org.springframework:spring-expression",
      "version": "4.3.23.RELEASE",
      "licenses": [
        {
          "license": {
            "name": "Apache License, Version 2.0"
          }
        }
      ],
      "purl": "pkg:maven/org.springframework/spring-expression@4.3.23.RELEASE",
      "properties": [
        {
          "name": "aquasecurity:trivy:PkgID",
          "value": "org.springframework:spring-expression:4.3.23.RELEASE"
        },
        {
          "name": "aquasecurity:trivy:PkgType",
          "value": "pom"
        }
      ]
    },
    {
      "bom-ref": "pkg:maven/org.springframework/spring-jdbc@5.1.4.RELEASE",
      "type": "library",
      "name": "org.springframework:spring-jdbc",
      "version": "5.1.4.RELEASE",
      "licenses": [
        {
          "license": {
            "name": "Apache License, Version 2.0"
          }
        }
      ],
      "purl": "pkg:maven/org.springframework/spring-jdbc@5.1.4.RELEASE",
      "properties": [
        {
          "name": "aquasecurity:trivy:PkgID",
          "value": "org.springframework:spring-jdbc:5.1.4.RELEASE"
        },
        {
          "name": "aquasecurity:trivy:PkgType",
          "value": "pom"
        }
      ]
    },
    {
      "bom-ref": "pkg:maven/org.springframework/spring-tx@5.1.4.RELEASE",
      "type": "library",
      "name": "org.springframework:spring-tx",
      "version": "5.1.4.RELEASE",
      "licenses": [
        {
          "license": {
            "name": "Apache License, Version 2.0"
          }
        }
      ],
      "purl": "pkg:maven/org.springframework/spring-tx@5.1.4.RELEASE",
      "properties": [
        {
          "name": "aquasecurity:trivy:PkgID",
          "value": "org.springframework:spring-tx:5.1.4.RELEASE"
        },
        {
          "name": "aquasecurity:trivy:PkgType",
          "value": "pom"
        }
      ]
    },
    {
      "bom-ref": "pkg:maven/org.springframework/spring-web@4.3.23.RELEASE",
      "type": "library",
      "name": "org.springframework:spring-web",
      "version": "4.3.23.RELEASE",
      "licenses": [
        {
          "license": {
            "name": "Apache License, Version 2.0"
          }
        }
      ],
      "purl": "pkg:maven/org.springframework/spring-web@4.3.23.RELEASE",
      "properties": [
        {
          "name": "aquasecurity:trivy:PkgID",
          "value": "org.springframework:spring-web:4.3.23.RELEASE"
        },
        {
          "name": "aquasecurity:trivy:PkgType",
          "value": "pom"
        }
      ]
    },
    {
      "bom-ref": "pkg:maven/org.springframework/spring-webmvc@4.3.23.RELEASE",
      "type": "library",
      "name": "org.springframework:spring-webmvc",
      "version": "4.3.23.RELEASE",
      "licenses": [
        {
          "license": {
            "name": "Apache License, Version 2.0"
          }
        }
      ],
      "purl": "pkg:maven/org.springframework/spring-webmvc@4.3.23.RELEASE",
      "properties": [
        {
          "name": "aquasecurity:trivy:PkgID",
          "value": "org.springframework:spring-webmvc:4.3.23.RELEASE"
        },
        {
          "name": "aquasecurity:trivy:PkgType",
          "value": "pom"
        }
      ]
    },
    {
      "bom-ref": "pkg:maven/org.xerial.snappy/snappy-java@1.1.7.3",
      "type": "library",
      "name": "org.xerial.snappy:snappy-java",
      "version": "1.1.7.3",
      "licenses": [
        {
          "license": {
            "name": "The Apache Software License, Version 2.0"
          }
        }
      ],
      "purl": "pkg:maven/org.xerial.snappy/snappy-java@1.1.7.3",
      "properties": [
        {
          "name": "aquasecurity:trivy:PkgID",
          "value": "org.xerial.snappy:snappy-java:1.1.7.3"
        },
        {
          "name": "aquasecurity:trivy:PkgType",
          "value": "pom"
        }
      ]
    },
    {
      "bom-ref": "pkg:maven/org.xerial/sqlite-jdbc@3.28.0",
      "type": "library",
      "name": "org.xerial:sqlite-jdbc",
      "version": "3.28.0",
      "licenses": [
        {
          "license": {
            "name": "The Apache Software License, Version 2.0"
          }
        }
      ],
      "purl": "pkg:maven/org.xerial/sqlite-jdbc@3.28.0",
      "properties": [
        {
          "name": "aquasecurity:trivy:PkgID",
          "value": "org.xerial:sqlite-jdbc:3.28.0"
        },
        {
          "name": "aquasecurity:trivy:PkgType",
          "value": "pom"
        }
      ]
    }
  ],
  "dependencies": [
    {
      "ref": "0864bf85-5434-4a36-befc-b721f7eb12d6",
      "dependsOn": [
        "pkg:maven/br.com.wasp/common-database@1.0-SNAPSHOT",
        "pkg:maven/com.google.code.gson/gson@2.8.6",
        "pkg:maven/org.apache.ant/ant-antunit@1.3",
        "pkg:maven/org.apache.derby/derby@10.14.2.0",
        "pkg:maven/org.apache.kafka/kafka-clients@2.3.1",
        "pkg:maven/org.slf4j/slf4j-simple@1.7.29",
        "pkg:maven/org.xerial/sqlite-jdbc@3.28.0"
      ]
    },
    {
      "ref": "0dabfef1-fdda-4516-a384-7e88623de411",
      "dependsOn": [
        "pkg:maven/br.com.wasp/common-database@1.0-SNAPSHOT",
        "pkg:maven/br.com.wasp/common-kafka@1.0-SNAPSHOT",
        "pkg:maven/br.com.wasp/service-http-ecommerce@1.0-SNAPSHOT",
        "pkg:maven/com.google.code.gson/gson@2.8.6",
        "pkg:maven/org.apache.kafka/kafka-clients@2.3.1",
        "pkg:maven/org.eclipse.jetty/jetty-servlet@9.4.23.v20191118",
        "pkg:maven/org.slf4j/slf4j-simple@1.7.29"
      ]
    },
    {
      "ref": "1eb5adb3-19be-4b74-a3c1-d2accf4b2998",
      "dependsOn": [
        "pkg:maven/br.com.wasp/common-database@1.0-SNAPSHOT",
        "pkg:maven/com.alibaba/druid-spring-boot-starter@1.1.10",
        "pkg:maven/com.baomidou/mybatis-plus-boot-starter@3.1.1",
        "pkg:maven/com.google.code.gson/gson@2.8.6",
        "pkg:maven/io.seata/seata-all@1.1.0",
        "pkg:maven/mysql/mysql-connector-java@5.1.39",
        "pkg:maven/org.apache.kafka/kafka-clients@2.3.1",
        "pkg:maven/org.slf4j/slf4j-simple@1.7.29",
        "pkg:maven/org.xerial/sqlite-jdbc@3.28.0"
      ]
    },
    {
      "ref": "342cb33c-2228-4991-87e0-2cdcbca62cad",
      "dependsOn": [
        "pkg:maven/br.com.wasp/common-kafka@1.0-SNAPSHOT",
        "pkg:maven/br.com.wasp/service-reading-report@1.0-SNAPSHOT",
        "pkg:maven/com.google.code.gson/gson@2.8.6",
        "pkg:maven/org.apache.kafka/kafka-clients@2.3.1",
        "pkg:maven/org.slf4j/slf4j-simple@1.7.29"
      ]
    },
    {
      "ref": "392cebe1-7c0d-4198-bbc7-25ba8009cbc6",
      "dependsOn": [
        "pkg:maven/br.com.wasp/common-database@1.0-SNAPSHOT",
        "pkg:maven/br.com.wasp/common-kafka@1.0-SNAPSHOT",
        "pkg:maven/br.com.wasp/service-users@1.0-SNAPSHOT",
        "pkg:maven/com.google.code.gson/gson@2.8.6",
        "pkg:maven/org.apache.kafka/kafka-clients@2.3.1",
        "pkg:maven/org.slf4j/slf4j-simple@1.7.29"
      ]
    },
    {
      "ref": "4103d9a3-9e1f-4a93-8d2c-07c11e141881",
      "dependsOn": [
        "pkg:maven/br.com.wasp/common-kafka@1.0-SNAPSHOT",
        "pkg:maven/br.com.wasp/service-email@1.0-SNAPSHOT",
        "pkg:maven/com.google.code.gson/gson@2.8.6",
        "pkg:maven/org.apache.kafka/kafka-clients@2.3.1",
        "pkg:maven/org.slf4j/slf4j-simple@1.7.29"
      ]
    },
    {
      "ref": "438a2713-4133-4090-8939-bbc400fa1971",
      "dependsOn": [
        "pkg:maven/br.com.wasp/common-kafka@1.0-SNAPSHOT",
        "pkg:maven/br.com.wasp/service-email-new-order@1.0-SNAPSHOT",
        "pkg:maven/com.google.code.gson/gson@2.8.6",
        "pkg:maven/org.apache.kafka/kafka-clients@2.3.1",
        "pkg:maven/org.slf4j/slf4j-simple@1.7.29"
      ]
    },
    {
      "ref": "45cebb50-92f5-4991-81b0-92a1cbe09390",
      "dependsOn": [
        "pkg:maven/br.com.wasp/common-kafka@1.0-SNAPSHOT",
        "pkg:maven/br.com.wasp/service-new-order@1.0-SNAPSHOT",
        "pkg:maven/com.google.code.gson/gson@2.8.6",
        "pkg:maven/org.apache.kafka/kafka-clients@2.3.1",
        "pkg:maven/org.slf4j/slf4j-simple@1.7.29"
      ]
    },
    {
      "ref": "82cca740-2d71-4c4a-bf7d-a5484b9ba1ec",
      "dependsOn": [
        "pkg:maven/br.com.wasp/common-database@1.0-SNAPSHOT",
        "pkg:maven/com.google.code.gson/gson@2.8.6",
        "pkg:maven/org.apache.kafka/kafka-clients@2.3.1",
        "pkg:maven/org.slf4j/slf4j-simple@1.7.29",
        "pkg:maven/org.xerial/sqlite-jdbc@3.28.0"
      ]
    },
    {
      "ref": "8e83ad54-f8ae-4885-9fff-365d146c66e8",
      "dependsOn": [
        "0864bf85-5434-4a36-befc-b721f7eb12d6",
        "0dabfef1-fdda-4516-a384-7e88623de411",
        "1eb5adb3-19be-4b74-a3c1-d2accf4b2998",
        "342cb33c-2228-4991-87e0-2cdcbca62cad",
        "392cebe1-7c0d-4198-bbc7-25ba8009cbc6",
        "4103d9a3-9e1f-4a93-8d2c-07c11e141881",
        "438a2713-4133-4090-8939-bbc400fa1971",
        "45cebb50-92f5-4991-81b0-92a1cbe09390",
        "82cca740-2d71-4c4a-bf7d-a5484b9ba1ec",
        "a94be8c2-1cbc-49e2-a4ce-4d4450025eab",
        "db225295-c694-4628-8640-c2ad1f711942",
        "eaf0de27-628e-4572-ab12-6c3a9b98ecc1",
        "f632edda-480c-463c-8511-d7faf05ca7c7"
      ]
    },
    {
      "ref": "a94be8c2-1cbc-49e2-a4ce-4d4450025eab",
      "dependsOn": [
        "pkg:maven/br.com.wasp/common-database@1.0-SNAPSHOT",
        "pkg:maven/br.com.wasp/common-kafka@1.0-SNAPSHOT",
        "pkg:maven/br.com.wasp/ecommerce@1.0-SNAPSHOT",
        "pkg:maven/br.com.wasp/service-email-new-order@1.0-SNAPSHOT",
        "pkg:maven/br.com.wasp/service-email@1.0-SNAPSHOT",
        "pkg:maven/br.com.wasp/service-fraud-detector@1.0-SNAPSHOT",
        "pkg:maven/br.com.wasp/service-http-ecommerce@1.0-SNAPSHOT",
        "pkg:maven/br.com.wasp/service-log@1.0-SNAPSHOT",
        "pkg:maven/br.com.wasp/service-new-order@1.0-SNAPSHOT",
        "pkg:maven/br.com.wasp/service-reading-report@1.0-SNAPSHOT",
        "pkg:maven/br.com.wasp/service-users@1.0-SNAPSHOT",
        "pkg:maven/com.google.code.gson/gson@2.8.6",
        "pkg:maven/org.apache.kafka/kafka-clients@2.3.1",
        "pkg:maven/org.eclipse.jetty/jetty-servlet@9.4.23.v20191118",
        "pkg:maven/org.slf4j/slf4j-simple@1.7.29"
      ]
    },
    {
      "ref": "db225295-c694-4628-8640-c2ad1f711942",
      "dependsOn": [
        "pkg:maven/br.com.wasp/common-kafka@1.0-SNAPSHOT",
        "pkg:maven/com.google.code.gson/gson@2.8.6",
        "pkg:maven/org.apache.kafka/kafka-clients@2.3.1",
        "pkg:maven/org.slf4j/slf4j-simple@1.7.29"
      ]
    },
    {
      "ref": "eaf0de27-628e-4572-ab12-6c3a9b98ecc1",
      "dependsOn": [
        "pkg:maven/br.com.wasp/common-database@1.0-SNAPSHOT",
        "pkg:maven/br.com.wasp/common-kafka@1.0-SNAPSHOT",
        "pkg:maven/br.com.wasp/service-fraud-detector@1.0-SNAPSHOT",
        "pkg:maven/com.google.code.gson/gson@2.8.6",
        "pkg:maven/org.apache.kafka/kafka-clients@2.3.1",
        "pkg:maven/org.slf4j/slf4j-simple@1.7.29"
      ]
    },
    {
      "ref": "f632edda-480c-463c-8511-d7faf05ca7c7",
      "dependsOn": [
        "pkg:maven/br.com.wasp/common-kafka@1.0-SNAPSHOT",
        "pkg:maven/br.com.wasp/service-log@1.0-SNAPSHOT",
        "pkg:maven/com.google.code.gson/gson@2.8.6",
        "pkg:maven/org.apache.kafka/kafka-clients@2.3.1",
        "pkg:maven/org.slf4j/slf4j-simple@1.7.29"
      ]
    },
    {
      "ref": "pkg:maven/aopalliance/aopalliance@1.0",
      "dependsOn": []
    },
    {
      "ref": "pkg:maven/br.com.wasp/common-database@1.0-SNAPSHOT",
      "dependsOn": []
    },
    {
      "ref": "pkg:maven/br.com.wasp/common-kafka@1.0-SNAPSHOT",
      "dependsOn": []
    },
    {
      "ref": "pkg:maven/br.com.wasp/ecommerce@1.0-SNAPSHOT",
      "dependsOn": [
        "pkg:maven/com.google.code.gson/gson@2.8.6",
        "pkg:maven/org.apache.kafka/kafka-clients@2.3.1",
        "pkg:maven/org.slf4j/slf4j-simple@1.7.29"
      ]
    },
    {
      "ref": "pkg:maven/br.com.wasp/service-email-new-order@1.0-SNAPSHOT",
      "dependsOn": [
        "pkg:maven/br.com.wasp/common-kafka@1.0-SNAPSHOT",
        "pkg:maven/com.google.code.gson/gson@2.8.6",
        "pkg:maven/org.apache.kafka/kafka-clients@2.3.1",
        "pkg:maven/org.slf4j/slf4j-simple@1.7.29"
      ]
    },
    {
      "ref": "pkg:maven/br.com.wasp/service-email@1.0-SNAPSHOT",
      "dependsOn": [
        "pkg:maven/br.com.wasp/common-kafka@1.0-SNAPSHOT",
        "pkg:maven/com.google.code.gson/gson@2.8.6",
        "pkg:maven/org.apache.kafka/kafka-clients@2.3.1",
        "pkg:maven/org.slf4j/slf4j-simple@1.7.29"
      ]
    },
    {
      "ref": "pkg:maven/br.com.wasp/service-fraud-detector@1.0-SNAPSHOT",
      "dependsOn": [
        "pkg:maven/br.com.wasp/common-database@1.0-SNAPSHOT",
        "pkg:maven/br.com.wasp/common-kafka@1.0-SNAPSHOT",
        "pkg:maven/com.google.code.gson/gson@2.8.6",
        "pkg:maven/org.apache.kafka/kafka-clients@2.3.1",
        "pkg:maven/org.slf4j/slf4j-simple@1.7.29"
      ]
    },
    {
      "ref": "pkg:maven/br.com.wasp/service-http-ecommerce@1.0-SNAPSHOT",
      "dependsOn": [
        "pkg:maven/br.com.wasp/common-database@1.0-SNAPSHOT",
        "pkg:maven/br.com.wasp/common-kafka@1.0-SNAPSHOT",
        "pkg:maven/com.google.code.gson/gson@2.8.6",
        "pkg:maven/org.apache.kafka/kafka-clients@2.3.1",
        "pkg:maven/org.eclipse.jetty/jetty-servlet@9.4.23.v20191118",
        "pkg:maven/org.slf4j/slf4j-simple@1.7.29"
      ]
    },
    {
      "ref": "pkg:maven/br.com.wasp/service-log@1.0-SNAPSHOT",
      "dependsOn": [
        "pkg:maven/br.com.wasp/common-kafka@1.0-SNAPSHOT",
        "pkg:maven/com.google.code.gson/gson@2.8.6",
        "pkg:maven/org.apache.kafka/kafka-clients@2.3.1",
        "pkg:maven/org.slf4j/slf4j-simple@1.7.29"
      ]
    },
    {
      "ref": "pkg:maven/br.com.wasp/service-new-order@1.0-SNAPSHOT",
      "dependsOn": [
        "pkg:maven/br.com.wasp/common-kafka@1.0-SNAPSHOT",
        "pkg:maven/com.google.code.gson/gson@2.8.6",
        "pkg:maven/org.apache.kafka/kafka-clients@2.3.1",
        "pkg:maven/org.slf4j/slf4j-simple@1.7.29"
      ]
    },
    {
      "ref": "pkg:maven/br.com.wasp/service-reading-report@1.0-SNAPSHOT",
      "dependsOn": [
        "pkg:maven/br.com.wasp/common-kafka@1.0-SNAPSHOT",
        "pkg:maven/com.google.code.gson/gson@2.8.6",
        "pkg:maven/org.apache.kafka/kafka-clients@2.3.1",
        "pkg:maven/org.slf4j/slf4j-simple@1.7.29"
      ]
    },
    {
      "ref": "pkg:maven/br.com.wasp/service-users@1.0-SNAPSHOT",
      "dependsOn": [
        "pkg:maven/br.com.wasp/common-database@1.0-SNAPSHOT",
        "pkg:maven/br.com.wasp/common-kafka@1.0-SNAPSHOT",
        "pkg:maven/com.google.code.gson/gson@2.8.6",
        "pkg:maven/org.apache.kafka/kafka-clients@2.3.1",
        "pkg:maven/org.slf4j/slf4j-simple@1.7.29"
      ]
    },
    {
      "ref": "pkg:maven/cglib/cglib@3.1",
      "dependsOn": [
        "pkg:maven/org.ow2.asm/asm@4.2"
      ]
    },
    {
      "ref": "pkg:maven/ch.qos.logback/logback-classic@1.2.3",
      "dependsOn": [
        "pkg:maven/ch.qos.logback/logback-core@1.2.3",
        "pkg:maven/org.slf4j/slf4j-api@1.7.26"
      ]
    },
    {
      "ref": "pkg:maven/ch.qos.logback/logback-core@1.2.3",
      "dependsOn": []
    },
    {
      "ref": "pkg:maven/com.alibaba/druid-spring-boot-starter@1.1.10",
      "dependsOn": [
        "pkg:maven/com.alibaba/druid@1.1.10",
        "pkg:maven/org.slf4j/slf4j-api@1.7.26",
        "pkg:maven/org.springframework.boot/spring-boot-autoconfigure@1.5.12.RELEASE"
      ]
    },
    {
      "ref": "pkg:maven/com.alibaba/druid@1.1.10",
      "dependsOn": []
    },
    {
      "ref": "pkg:maven/com.alibaba/fastjson@1.2.60",
      "dependsOn": []
    },
    {
      "ref": "pkg:maven/com.baomidou/mybatis-plus-annotation@3.1.1",
      "dependsOn": []
    },
    {
      "ref": "pkg:maven/com.baomidou/mybatis-plus-boot-starter@3.1.1",
      "dependsOn": [
        "pkg:maven/com.baomidou/mybatis-plus@3.1.1",
        "pkg:maven/org.springframework.boot/spring-boot-autoconfigure@1.5.12.RELEASE",
        "pkg:maven/org.springframework.boot/spring-boot-starter-jdbc@2.1.2.RELEASE"
      ]
    },
    {
      "ref": "pkg:maven/com.baomidou/mybatis-plus-core@3.1.1",
      "dependsOn": [
        "pkg:maven/com.baomidou/mybatis-plus-annotation@3.1.1",
        "pkg:maven/com.github.jsqlparser/jsqlparser@1.2",
        "pkg:maven/org.mybatis/mybatis@3.5.1"
      ]
    },
    {
      "ref": "pkg:maven/com.baomidou/mybatis-plus-extension@3.1.1",
      "dependsOn": [
        "pkg:maven/com.baomidou/mybatis-plus-core@3.1.1",
        "pkg:maven/org.mybatis/mybatis-spring@2.0.1"
      ]
    },
    {
      "ref": "pkg:maven/com.baomidou/mybatis-plus@3.1.1",
      "dependsOn": [
        "pkg:maven/com.baomidou/mybatis-plus-extension@3.1.1"
      ]
    },
    {
      "ref": "pkg:maven/com.github.ben-manes.caffeine/caffeine@2.7.0",
      "dependsOn": [
        "pkg:maven/com.google.errorprone/error_prone_annotations@2.3.3",
        "pkg:maven/org.checkerframework/checker-qual@2.6.0"
      ]
    },
    {
      "ref": "pkg:maven/com.github.jsqlparser/jsqlparser@1.2",
      "dependsOn": []
    },
    {
      "ref": "pkg:maven/com.github.luben/zstd-jni@1.4.0-1",
      "dependsOn": []
    },
    {
      "ref": "pkg:maven/com.google.code.gson/gson@2.8.6",
      "dependsOn": []
    },
    {
      "ref": "pkg:maven/com.google.errorprone/error_prone_annotations@2.3.3",
      "dependsOn": []
    },
    {
      "ref": "pkg:maven/com.google.protobuf/protobuf-java@3.7.1",
      "dependsOn": []
    },
    {
      "ref": "pkg:maven/com.typesafe/config@1.2.1",
      "dependsOn": []
    },
    {
      "ref": "pkg:maven/com.zaxxer/HikariCP@3.2.0",
      "dependsOn": [
        "pkg:maven/org.slf4j/slf4j-api@1.7.26"
      ]
    },
    {
      "ref": "pkg:maven/commons-lang/commons-lang@2.6",
      "dependsOn": []
    },
    {
      "ref": "pkg:maven/commons-logging/commons-logging@1.2",
      "dependsOn": []
    },
    {
      "ref": "pkg:maven/commons-pool/commons-pool@1.6",
      "dependsOn": []
    },
    {
      "ref": "pkg:maven/io.netty/netty-all@4.1.30.Final",
      "dependsOn": []
    },
    {
      "ref": "pkg:maven/io.seata/seata-all@1.1.0",
      "dependsOn": [
        "pkg:maven/aopalliance/aopalliance@1.0",
        "pkg:maven/cglib/cglib@3.1",
        "pkg:maven/com.alibaba/druid@1.1.10",
        "pkg:maven/com.alibaba/fastjson@1.2.60",
        "pkg:maven/com.github.ben-manes.caffeine/caffeine@2.7.0",
        "pkg:maven/com.google.protobuf/protobuf-java@3.7.1",
        "pkg:maven/com.typesafe/config@1.2.1",
        "pkg:maven/commons-lang/commons-lang@2.6",
        "pkg:maven/commons-pool/commons-pool@1.6",
        "pkg:maven/io.netty/netty-all@4.1.30.Final",
        "pkg:maven/org.apache.commons/commons-pool2@2.4.2",
        "pkg:maven/org.postgresql/postgresql@42.1.4",
        "pkg:maven/org.slf4j/slf4j-api@1.7.26",
        "pkg:maven/org.springframework/spring-aop@4.3.23.RELEASE",
        "pkg:maven/org.springframework/spring-beans@4.3.23.RELEASE",
        "pkg:maven/org.springframework/spring-context@4.3.23.RELEASE",
        "pkg:maven/org.springframework/spring-core@4.3.23.RELEASE",
        "pkg:maven/org.springframework/spring-webmvc@4.3.23.RELEASE"
      ]
    },
    {
      "ref": "pkg:maven/javax.annotation/javax.annotation-api@1.3.2",
      "dependsOn": []
    },
    {
      "ref": "pkg:maven/javax.servlet/javax.servlet-api@3.1.0",
      "dependsOn": []
    },
    {
      "ref": "pkg:maven/mysql/mysql-connector-java@5.1.39",
      "dependsOn": []
    },
    {
      "ref": "pkg:maven/org.apache.ant/ant-antunit@1.3",
      "dependsOn": [
        "pkg:maven/org.apache.ant/ant@1.7.1"
      ]
    },
    {
      "ref": "pkg:maven/org.apache.ant/ant@1.7.1",
      "dependsOn": []
    },
    {
      "ref": "pkg:maven/org.apache.commons/commons-pool2@2.4.2",
      "dependsOn": []
    },
    {
      "ref": "pkg:maven/org.apache.derby/derby@10.14.2.0",
      "dependsOn": []
    },
    {
      "ref": "pkg:maven/org.apache.kafka/kafka-clients@2.3.1",
      "dependsOn": [
        "pkg:maven/com.github.luben/zstd-jni@1.4.0-1",
        "pkg:maven/org.lz4/lz4-java@1.6.0",
        "pkg:maven/org.slf4j/slf4j-api@1.7.26",
        "pkg:maven/org.xerial.snappy/snappy-java@1.1.7.3"
      ]
    },
    {
      "ref": "pkg:maven/org.apache.logging.log4j/log4j-api@2.11.1",
      "dependsOn": []
    },
    {
      "ref": "pkg:maven/org.apache.logging.log4j/log4j-to-slf4j@2.11.1",
      "dependsOn": [
        "pkg:maven/org.apache.logging.log4j/log4j-api@2.11.1",
        "pkg:maven/org.slf4j/slf4j-api@1.7.26"
      ]
    },
    {
      "ref": "pkg:maven/org.checkerframework/checker-qual@2.6.0",
      "dependsOn": []
    },
    {
      "ref": "pkg:maven/org.eclipse.jetty/jetty-http@9.4.23.v20191118",
      "dependsOn": [
        "pkg:maven/org.eclipse.jetty/jetty-io@9.4.23.v20191118",
        "pkg:maven/org.eclipse.jetty/jetty-util@9.4.23.v20191118"
      ]
    },
    {
      "ref": "pkg:maven/org.eclipse.jetty/jetty-io@9.4.23.v20191118",
      "dependsOn": [
        "pkg:maven/org.eclipse.jetty/jetty-util@9.4.23.v20191118"
      ]
    },
    {
      "ref": "pkg:maven/org.eclipse.jetty/jetty-security@9.4.23.v20191118",
      "dependsOn": [
        "pkg:maven/org.eclipse.jetty/jetty-server@9.4.23.v20191118"
      ]
    },
    {
      "ref": "pkg:maven/org.eclipse.jetty/jetty-server@9.4.23.v20191118",
      "dependsOn": [
        "pkg:maven/javax.servlet/javax.servlet-api@3.1.0",
        "pkg:maven/org.eclipse.jetty/jetty-http@9.4.23.v20191118",
        "pkg:maven/org.eclipse.jetty/jetty-io@9.4.23.v20191118"
      ]
    },
    {
      "ref": "pkg:maven/org.eclipse.jetty/jetty-servlet@9.4.23.v20191118",
      "dependsOn": [
        "pkg:maven/org.eclipse.jetty/jetty-security@9.4.23.v20191118"
      ]
    },
    {
      "ref": "pkg:maven/org.eclipse.jetty/jetty-util@9.4.23.v20191118",
      "dependsOn": []
    },
    {
      "ref": "pkg:maven/org.lz4/lz4-java@1.6.0",
      "dependsOn": []
    },
    {
      "ref": "pkg:maven/org.mybatis/mybatis-spring@2.0.1",
      "dependsOn": []
    },
    {
      "ref": "pkg:maven/org.mybatis/mybatis@3.5.1",
      "dependsOn": []
    },
    {
      "ref": "pkg:maven/org.ow2.asm/asm@4.2",
      "dependsOn": []
    },
    {
      "ref": "pkg:maven/org.postgresql/postgresql@42.1.4",
      "dependsOn": []
    },
    {
      "ref": "pkg:maven/org.slf4j/jul-to-slf4j@1.7.25",
      "dependsOn": [
        "pkg:maven/org.slf4j/slf4j-api@1.7.26"
      ]
    },
    {
      "ref": "pkg:maven/org.slf4j/slf4j-api@1.7.26",
      "dependsOn": []
    },
    {
      "ref": "pkg:maven/org.slf4j/slf4j-simple@1.7.29",
      "dependsOn": [
        "pkg:maven/org.slf4j/slf4j-api@1.7.26"
      ]
    },
    {
      "ref": "pkg:maven/org.springframework.boot/spring-boot-autoconfigure@1.5.12.RELEASE",
      "dependsOn": [
        "pkg:maven/org.springframework.boot/spring-boot@1.5.12.RELEASE"
      ]
    },
    {
      "ref": "pkg:maven/org.springframework.boot/spring-boot-starter-jdbc@2.1.2.RELEASE",
      "dependsOn": [
        "pkg:maven/com.zaxxer/HikariCP@3.2.0",
        "pkg:maven/org.springframework.boot/spring-boot-starter@2.1.2.RELEASE",
        "pkg:maven/org.springframework/spring-jdbc@5.1.4.RELEASE"
      ]
    },
    {
      "ref": "pkg:maven/org.springframework.boot/spring-boot-starter-logging@2.1.2.RELEASE",
      "dependsOn": [
        "pkg:maven/ch.qos.logback/logback-classic@1.2.3",
        "pkg:maven/org.apache.logging.log4j/log4j-to-slf4j@2.11.1",
        "pkg:maven/org.slf4j/jul-to-slf4j@1.7.25"
      ]
    },
    {
      "ref": "pkg:maven/org.springframework.boot/spring-boot-starter@2.1.2.RELEASE",
      "dependsOn": [
        "pkg:maven/javax.annotation/javax.annotation-api@1.3.2",
        "pkg:maven/org.springframework.boot/spring-boot-autoconfigure@1.5.12.RELEASE",
        "pkg:maven/org.springframework.boot/spring-boot-starter-logging@2.1.2.RELEASE",
        "pkg:maven/org.springframework.boot/spring-boot@1.5.12.RELEASE",
        "pkg:maven/org.springframework/spring-core@4.3.23.RELEASE"
      ]
    },
    {
      "ref": "pkg:maven/org.springframework.boot/spring-boot@1.5.12.RELEASE",
      "dependsOn": [
        "pkg:maven/org.springframework/spring-context@4.3.23.RELEASE",
        "pkg:maven/org.springframework/spring-core@4.3.23.RELEASE"
      ]
    },
    {
      "ref": "pkg:maven/org.springframework/spring-aop@4.3.23.RELEASE",
      "dependsOn": [
        "pkg:maven/org.springframework/spring-beans@4.3.23.RELEASE",
        "pkg:maven/org.springframework/spring-core@4.3.23.RELEASE"
      ]
    },
    {
      "ref": "pkg:maven/org.springframework/spring-beans@4.3.23.RELEASE",
      "dependsOn": [
        "pkg:maven/org.springframework/spring-core@4.3.23.RELEASE"
      ]
    },
    {
      "ref": "pkg:maven/org.springframework/spring-context@4.3.23.RELEASE",
      "dependsOn": [
        "pkg:maven/org.springframework/spring-aop@4.3.23.RELEASE",
        "pkg:maven/org.springframework/spring-beans@4.3.23.RELEASE",
        "pkg:maven/org.springframework/spring-core@4.3.23.RELEASE",
        "pkg:maven/org.springframework/spring-expression@4.3.23.RELEASE"
      ]
    },
    {
      "ref": "pkg:maven/org.springframework/spring-core@4.3.23.RELEASE",
      "dependsOn": [
        "pkg:maven/commons-logging/commons-logging@1.2"
      ]
    },
    {
      "ref": "pkg:maven/org.springframework/spring-expression@4.3.23.RELEASE",
      "dependsOn": [
        "pkg:maven/org.springframework/spring-core@4.3.23.RELEASE"
      ]
    },
    {
      "ref": "pkg:maven/org.springframework/spring-jdbc@5.1.4.RELEASE",
      "dependsOn": [
        "pkg:maven/org.springframework/spring-beans@4.3.23.RELEASE",
        "pkg:maven/org.springframework/spring-core@4.3.23.RELEASE",
        "pkg:maven/org.springframework/spring-tx@5.1.4.RELEASE"
      ]
    },
    {
      "ref": "pkg:maven/org.springframework/spring-tx@5.1.4.RELEASE",
      "dependsOn": [
        "pkg:maven/org.springframework/spring-beans@4.3.23.RELEASE",
        "pkg:maven/org.springframework/spring-core@4.3.23.RELEASE"
      ]
    },
    {
      "ref": "pkg:maven/org.springframework/spring-web@4.3.23.RELEASE",
      "dependsOn": [
        "pkg:maven/org.springframework/spring-aop@4.3.23.RELEASE",
        "pkg:maven/org.springframework/spring-beans@4.3.23.RELEASE",
        "pkg:maven/org.springframework/spring-context@4.3.23.RELEASE",
        "pkg:maven/org.springframework/spring-core@4.3.23.RELEASE"
      ]
    },
    {
      "ref": "pkg:maven/org.springframework/spring-webmvc@4.3.23.RELEASE",
      "dependsOn": [
        "pkg:maven/org.springframework/spring-aop@4.3.23.RELEASE",
        "pkg:maven/org.springframework/spring-beans@4.3.23.RELEASE",
        "pkg:maven/org.springframework/spring-context@4.3.23.RELEASE",
        "pkg:maven/org.springframework/spring-core@4.3.23.RELEASE",
        "pkg:maven/org.springframework/spring-expression@4.3.23.RELEASE",
        "pkg:maven/org.springframework/spring-web@4.3.23.RELEASE"
      ]
    },
    {
      "ref": "pkg:maven/org.xerial.snappy/snappy-java@1.1.7.3",
      "dependsOn": []
    },
    {
      "ref": "pkg:maven/org.xerial/sqlite-jdbc@3.28.0",
      "dependsOn": []
    }
  ],
  "vulnerabilities": []
}
